__init__.py
jyotishyamitra.py
input/birthdata.py
jyotishyamitra-1.4.0.dist-info/licenses/LICENSE
support/dashas.py
support/mod_ashtakavarga.py
support/mod_astrodata.py
support/mod_bala.py
support/mod_constants.py
support/mod_divisional.py
support/mod_general.py
support/mod_json.py
support/mod_lagna.py
support/mod_specialpoints.py
support/panchanga.py
jyotishyamitra-1.4.0.dist-info/METADATA
jyotishyamitra-1.4.0.dist-info/WHEEL
jyotishyamitra-1.4.0.dist-info/top_level.txt
jyotishyamitra-1.4.0.dist-info/RECORD
