Metadata-Version: 2.4
Name: jyotishyamitra
Version: 1.4.0
Summary: This package takes the birth data as input and computes indian vedic astrological data in a json file or python dictionary format
Author-email: Shyam Bhat <bhatshyam.modernastrologer@gmail.com>
Project-URL: Homepage, https://github.com/VicharaVandana/jyotishyamitra.git
Project-URL: Bug Tracker, https://github.com/VicharaVandana/jyotishyamitra/issues
Classifier: Programming Language :: Python :: 3
Classifier: License :: OSI Approved :: MIT License
Classifier: Operating System :: OS Independent
Requires-Python: >=3.7
License-File: LICENSE
Dynamic: license-file
